dailycovid/__init__.py
dailycovid/__main__.py
dailycovid/american_states.py
dailycovid/covid_plot.py
dailycovid/dailycovid.py
dailycovid-1.3.0.dist-info/entry_points.txt
dailycovid-1.3.0.dist-info/WHEEL
dailycovid-1.3.0.dist-info/METADATA
dailycovid-1.3.0.dist-info/RECORD
