Metadata-Version: 2.1
Name: dailycovid
Version: 1.3.0
Summary: U.S.A daily covid information.
Home-page: https://github.com/Fitzy1293/daily-covid
License: MIT
Keywords: COVID,Coronavirus
Author: fitzy1293
Author-email: berkshiremind@gmail.com
Requires-Python: >=3.5,<4.0
Classifier: License :: OSI Approved :: MIT License
Classifier: Programming Language :: Python :: 3
Classifier: Programming Language :: Python :: 3.5
Classifier: Programming Language :: Python :: 3.6
Classifier: Programming Language :: Python :: 3.7
Classifier: Programming Language :: Python :: 3.8
Classifier: Programming Language :: Python :: 3.9
Requires-Dist: matplotlib (>=3.0.0,<4.0.0)
Requires-Dist: numpy (>=1.0.0,<2.0.0)
Requires-Dist: pandas (>=1.0.0,<2.0.0)
Requires-Dist: requests (>=2.24.0,<3.0.0)
Project-URL: Repository, https://github.com/Fitzy1293/daily-covid
